setup.py
pclimate/__init__.py
pclimate/__main__.py
pclimate/functions.py
pclimate.egg-info/PKG-INFO
pclimate.egg-info/SOURCES.txt
pclimate.egg-info/dependency_links.txt
pclimate.egg-info/entry_points.txt
pclimate.egg-info/requires.txt
pclimate.egg-info/top_level.txt