Metadata-Version: 1.0
Name: pclimate
Version: 0.1.0
Summary: Simple CLI to retrieve PRISM data history at a point
Home-page: UNKNOWN
Author: Travis Williams
Author-email: travis.williams@colorado.edu
License: UNKNOWN
Platform: UNKNOWN
